xiuxian_bank/__init__.py
xiuxian_bank/bankconfig.py
xiuxian_bank-0.30.dist-info/METADATA
xiuxian_bank-0.30.dist-info/WHEEL
xiuxian_bank-0.30.dist-info/top_level.txt
xiuxian_bank-0.30.dist-info/RECORD
